{
  "Test": {
    "pass": "false",
    "title": "title test",
    "desc": "desc test",
    "fields_number": 2,
    "field_0": {
      "name": "name of field 1",
      "value": "value of field 1"
    },
    "field_1": {
      "name": "name of field 2",
      "value": "value of field 2"
    },
    "image": "png/main.png",
    "buttons_number": 2,
	"button_0": {
      "label": "test button 1",
      "url": "https://url_of_test_button_1.com/"
    },
    "button_1": {
      "label": "test button 2",
      "url": "https://url_of_test_button_2.com/"
    },
    "footer": "true",
	"text": "lgnlgnlgn"
  },
  "О боте": {
    "pass": "true",
    "title": "GOD SYSTEM Bot",
    "desc": "Stable v1.1",
    "fields_number": 6,
    "field_0": {
      "name": "Developed by",
      "value": "<@399839515134525440>",
      "inline": "True"
    },
    "field_1": {
      "name": "Developed on",
      "value": "Python (disnake)",
      "inline": "True"
    },
    "field_2": {
      "name": "",
      "value": "",
      "inline": "False"
    },
    "field_3": {
      "name": "VALORANT API by",
      "value": "[Henrik Mertens](https://github.com/Henrik-3/unofficial-valorant-api)",
      "inline": "True"
    },
    "field_4": {
      "name": "Hosted on",
      "value": "[pylexnodes.net](https://client.pylexnodes.net/)",
      "inline": "True"
    },
    "field_5": {
      "name": "Source code",
      "value": "[github.com](https://github.com/Legionidk/GOD-SYSTEM-Bot)",
      "inline": "False"
    }
  },
  "Команды экономики": {
    "pass": "true",
    "title": "Команды экономики",
    "desc": "",
    "fields_number": 8,
    "field_0": {
      "name": "/registration",
      "value": "Регистрация в боте",
      "inline": "True"
    },
    "field_1": {
      "name": "/balance",
      "value": "Просмотр баланса",
      "inline": "True"
    },
    "field_2": {
      "name": "",
      "value": "",
      "inline": "False"
    },
    "field_3": {
      "name": "/transfer [сумма] [получтель]",
      "value": "Перевод пользователю",
      "inline": "True"
    },
    "field_4": {
      "name": "/antibomj",
      "value": "Добирает пользователю баланс до установленного минимума (кд 24 часа)",
      "inline": "True"
    },
    "field_5": {
      "name": "",
      "value": "",
      "inline": "False"
    },
    "field_6": {
      "name": "/taxi",
      "value": "Работа таксистом (оплата 5.000, кд 30 минут)",
      "inline": "True"
    },
    "field_7": {
      "name": "/factory",
      "value": "Работа на заводе (оплата 10.000, кд 1 час)",
      "inline": "True"
    }
  },
  "Команды VALORANT": {
    "pass": "true",
    "title": "Команды VALORANT",
    "desc": "",
    "fields_number": 2,
    "field_0": {
      "name": "/valstats [ник] [тег] [регион]",
      "value": "Краткий обзор профиля VALORANT",
      "inline": "True"
    },
    "field_1": {
      "name": "valmatches [ник] [тег] [регион]",
      "value": "Отображает последние 5 рейтинговых игр",
      "inline": "True"
    }
  },
  "Админские команды": {
    "pass": "true",
    "title": "Админские команды",
    "desc": "",
    "fields_number": 12,
    "field_0": {
      "name": "Модерация",
      "value": "",
      "inline": "False"
    },
    "field_1": {
      "name": ".mute [@member] [hours: int]",
      "value": "Выдает тайм-аут пользователю на указанное кол-во часов (минимально 1, максимально 672)",
      "inline": "True"
    },
    "field_2": {
      "name": ".unmute [@member]",
      "value": "Убирает тайм-аут с пользователя",
      "inline": "True"
    },
    "field_3": {
      "name": "",
      "value": "",
      "inline": "False"
    },
    "field_4": {
      "name": ".kick [@member]",
      "value": "Кикает пользователя",
      "inline": "True"
    },
    "field_5": {
      "name": ".ban [@member]",
      "value": "Банит пользвателя",
      "inline": "True"
    },
    "field_6": {
      "name": "",
      "value": "",
      "inline": "False"
    },
    "field_7": {
      "name": ".clear [amount: int]",
      "value": "Очищает указанное кол-во сообщений",
      "inline": "True"
    },
    "field_8": {
      "name": "",
      "value": "",
      "inline": "False"
    },
    "field_9": {
      "name": "Экономика",
      "value": "",
      "inline": "False"
    },
    "field_10": {
      "name": ".godgive [amount: int] [@member]",
      "value": "Выдает валюту",
      "inline": "True"
    },
    "field_11": {
      "name": ".godtake [amount: int] [@member]",
      "value": "Забирает валюту",
      "inline": "True"
    }
  },
  "Список изменений": {
    "pass": "true",
    "title": "Список изменений",
    "desc": "Stable v1.1",
    "fields_number": 2,
    "field_0": {
      "name": "Обновления бота",
      "value": "- Теперь в статус бота передается его версия\n- Слеш команды теперь глобальны (работают на всех серверах)\n- Переработан embed для /valmatches\n- Переработана команда /about\n- Переработаны команды .embed и .embeds_view\n  - Теперь в пресетах необязательно выставлять параметру 'desc' значение 'none', можно оставить его пустым ('') - будет тот же эффект, что был при 'none'\n  - Добавлена проверка на пользователя (теперь команды смогут использовать только разрешенные id)\n  - Добавлена проверка разрешения использования пресетов для этих команд\n    - Для самих пресетов из embed_templates.json теперь обязателен новый параметр 'pass': 'true'/'false' (если false: оно не появляется в списке .embeds_view и не может быть использовано в .embed, true: противоположно)",
      "inline": "False"
    },
    "field_1": {
      "name": "Обновления скриптов",
      "value": "- Скрипт valorant_system.get_matches теперь отдает информацию о ранге",
      "inline": "False"
    }
  }
}